dictdiffer.py
setup.py
py_dictdiffer.egg-info/PKG-INFO
py_dictdiffer.egg-info/SOURCES.txt
py_dictdiffer.egg-info/dependency_links.txt
py_dictdiffer.egg-info/top_level.txt