Metadata-Version: 1.0
Name: py-dictdiffer
Version: 1.0
Summary: Python class to calculate the difference between two python dictionaries
Home-page: https://github.com/DisruptiveLabs/dictdiffer
Author: Disruptive Labs
Author-email: pypi+dictdiffer@comanage.com
License: UNKNOWN
Platform: UNKNOWN
